thread_py/__init__.py
thread_py-1.0.1.dist-info/LICENSE
thread_py-1.0.1.dist-info/METADATA
thread_py-1.0.1.dist-info/WHEEL
thread_py-1.0.1.dist-info/top_level.txt
thread_py-1.0.1.dist-info/RECORD
