Metadata-Version: 2.1
Name: thread_py
Version: 1.0.1
Summary: No Pain Multi-Processing.
Home-page: UNKNOWN
Author: Mohammad Mahdi Afshar
Author-email: me@mamad.dev
License: The Unlicensed
Platform: UNKNOWN
Classifier: Intended Audience :: Developers
Classifier: Topic :: Software Development :: Libraries :: Python Modules
Classifier: Topic :: Communications :: Chat
Classifier: Topic :: Internet
Classifier: Programming Language :: Python
Classifier: Programming Language :: Python :: 3
Classifier: Programming Language :: Python :: 3.7
Classifier: Programming Language :: Python :: 3.8
Classifier: Programming Language :: Python :: 3.9
Classifier: Programming Language :: Python :: 3.10
Requires-Python: >=3.8
License-File: LICENSE
